README.md
setup.py
arch/__init__.py
arch/raise_for_restful_exception.py
arch/restful_interceptor.py
arch/restful_response_code.py
ruiyun_flask_interceptor.egg-info/PKG-INFO
ruiyun_flask_interceptor.egg-info/SOURCES.txt
ruiyun_flask_interceptor.egg-info/dependency_links.txt
ruiyun_flask_interceptor.egg-info/top_level.txt
unit_test/__init__.py
unit_test/exception_test.py
unit_test/flask_test.py