Metadata-Version: 1.0
Name: ruiyun-flask-interceptor
Version: 0.0.4
Summary: 基于flask扩展的拦截框架
Home-page: https://github.com/chuckiefan/ruiyun-flask-interceptor
Author: chuckiefan
Author-email: chuckiefan@163.com
License: MIT Licence
Keywords: flask,restful,interceptor,AOP
Platform: UNKNOWN
